dominter/__init__.py
dominter/bootstrap4.py
dominter/dom.py
dominter/dominter.html
dominter/dominter.js
dominter/pure1.py
dominter-0.4.0.dist-info/DESCRIPTION.rst
dominter-0.4.0.dist-info/METADATA
dominter-0.4.0.dist-info/RECORD
dominter-0.4.0.dist-info/WHEEL
dominter-0.4.0.dist-info/metadata.json
dominter-0.4.0.dist-info/top_level.txt
